fast_validators-1.0.1.dist-info/METADATA
fast_validators-1.0.1.dist-info/RECORD
fast_validators-1.0.1.dist-info/WHEEL
fast_validators/__init__.py
fast_validators/_validator_js_ts.dll
fast_validators/_validator_rust.dll
fast_validators/_validator_tree.dll
fast_validators/base_validator.py
fast_validators/catalog.py
fast_validators/go_validator.py
fast_validators/js_ts_validator.py
fast_validators/json_validator.py
fast_validators/php_validator.py
fast_validators/python_validator.py
fast_validators/rust_validator.py
fast_validators/toml_validator.py
fast_validators/validator_tree.py
fast_validators/yaml_validator.py