Metadata-Version: 2.1
Name: fast_validators
Version: 1.0.1
Summary: Code validators
Requires-Dist: PyYAML (==6.0.2)
